bzfs-1.17.0.dist-info/licenses/LICENSE
bzfs_main/__init__.py
bzfs_main/argparse_actions.py
bzfs_main/argparse_cli.py
bzfs_main/bzfs.py
bzfs_main/bzfs_jobrunner.py
bzfs_main/compare_snapshot_lists.py
bzfs_main/configuration.py
bzfs_main/detect.py
bzfs_main/filter.py
bzfs_main/incremental_send_steps.py
bzfs_main/loggers.py
bzfs_main/parallel_batch_cmd.py
bzfs_main/period_anchors.py
bzfs_main/progress_reporter.py
bzfs_main/replication.py
bzfs_main/snapshot_cache.py
bzfs_main/util/__init__.py
bzfs_main/util/check_range.py
bzfs_main/util/connection.py
bzfs_main/util/connection_lease.py
bzfs_main/util/parallel_iterator.py
bzfs_main/util/parallel_tasktree.py
bzfs_main/util/parallel_tasktree_policy.py
bzfs_main/util/retry.py
bzfs_main/util/utils.py
bzfs_tests/__init__.py
bzfs_tests/abstract_testcase.py
bzfs_tests/bzfs_job_example.py
bzfs_tests/prune_bookmarks.py
bzfs_tests/test_all.py
bzfs_tests/test_argparse_actions.py
bzfs_tests/test_bzfs.py
bzfs_tests/test_compare_snapshot_lists.py
bzfs_tests/test_configuration.py
bzfs_tests/test_connection.py
bzfs_tests/test_connection_lease.py
bzfs_tests/test_detect.py
bzfs_tests/test_filter.py
bzfs_tests/test_incremental_send_steps.py
bzfs_tests/test_integrations.py
bzfs_tests/test_interner.py
bzfs_tests/test_jobrunner.py
bzfs_tests/test_loggers.py
bzfs_tests/test_parallel_batch_cmd.py
bzfs_tests/test_parallel_iterator.py
bzfs_tests/test_parallel_tasktree.py
bzfs_tests/test_parallel_tasktree_policy.py
bzfs_tests/test_period_anchors.py
bzfs_tests/test_progress_reporter.py
bzfs_tests/test_replication.py
bzfs_tests/test_retry.py
bzfs_tests/test_snapshot_cache.py
bzfs_tests/test_test_host_sh.py
bzfs_tests/test_utils.py
bzfs_tests/tools.py
bzfs_tests/zfs_util.py
bzfs-1.17.0.dist-info/METADATA
bzfs-1.17.0.dist-info/WHEEL
bzfs-1.17.0.dist-info/entry_points.txt
bzfs-1.17.0.dist-info/top_level.txt
bzfs-1.17.0.dist-info/RECORD
