Metadata-Version: 2.4
Name: bzfs
Version: 1.17.0
Summary: bzfs is a reliable near real-time, parallel replication and backup command-line tool for ZFS. It replicates snapshots from many local or remote source ZFS datasets (and their descendants) to local or remote destination datasets, using zfs send/receive and ssh, and can operate at sub-second intervals across large fleets of hosts.
Author-email: Wolfgang Hoschek <wolfgang.hoschek@mac.com>
Maintainer-email: Wolfgang Hoschek <wolfgang.hoschek@mac.com>
License: Apache License (2.0)
Project-URL: Homepage, https://github.com/whoschek/bzfs
Project-URL: Repository, https://github.com/whoschek/bzfs
Project-URL: Tests, https://github.com/whoschek/bzfs/actions/workflows/python-app.yml?query=event%3Aschedule
Project-URL: Coverage, https://whoschek.github.io/bzfs/coverage
Project-URL: Issues, https://github.com/whoschek/bzfs/issues
Project-URL: Changelog, https://github.com/whoschek/bzfs/blob/main/CHANGELOG.md
Project-URL: Distribution, https://pypi.org/project/bzfs
Keywords: bzfs,ZFS,snapshot,replication,backup,synchronization
Classifier: Development Status :: 5 - Production/Stable
Classifier: Environment :: Console
Classifier: Intended Audience :: Developers
Classifier: Intended Audience :: System Administrators
Classifier: License :: OSI Approved :: Apache Software License
Classifier: Operating System :: OS Independent
Classifier: Programming Language :: Python
Classifier: Programming Language :: Python :: 3
Classifier: Programming Language :: Python :: 3.9
Classifier: Programming Language :: Python :: 3.10
Classifier: Programming Language :: Python :: 3.11
Classifier: Programming Language :: Python :: 3.12
Classifier: Programming Language :: Python :: 3.13
Classifier: Programming Language :: Python :: 3.14
Classifier: Programming Language :: Python :: Implementation :: CPython
Classifier: Programming Language :: Python :: Implementation :: PyPy
Classifier: Topic :: Software Development :: Libraries :: Python Modules
Requires-Python: >=3.9
License-File: LICENSE
Provides-Extra: dev
Requires-Dist: argparse-manpage==4.7; extra == "dev"
Requires-Dist: genbadge[coverage]==1.1.3; extra == "dev"
Requires-Dist: commitizen==4.10.1; extra == "dev"
Requires-Dist: pre-commit==4.5.1; extra == "dev"
Requires-Dist: black==25.11.0; extra == "dev"
Requires-Dist: ruff==0.14.13; extra == "dev"
Requires-Dist: coverage>=7.6; extra == "dev"
Requires-Dist: mypy==1.19.1; extra == "dev"
Requires-Dist: shellcheck-py==0.11.0.1; extra == "dev"
Dynamic: license-file
